{
  "db_name": "PostgreSQL",
  "query": "\n        WITH current_round AS (\n            SELECT id\n            FROM santa_id_round\n            WHERE room_id = $1\n            ORDER BY round_number DESC\n            LIMIT 1\n        )\n        INSERT INTO santa_id_message (member_id, content, round_id)\n        SELECT $2, $3, current_round.id\n        FROM current_round\n        ",
  "describe": {
    "columns": [],
    "parameters": {
      "Left": [
        "Uuid",
        "Uuid",
        "TextArray"
      ]
    },
    "nullable": []
  },
  "hash": "a732ee0455e75985971268dcfef7d782e6a8a6ddd0808007492b7f17188cd4e0"
}
